README.rst
setup.cfg
setup.py
src/keras_lightning/__init__.py
src/keras_lightning/keras_lightning.py
src/keras_lightning.egg-info/PKG-INFO
src/keras_lightning.egg-info/SOURCES.txt
src/keras_lightning.egg-info/dependency_links.txt
src/keras_lightning.egg-info/requires.txt
src/keras_lightning.egg-info/top_level.txt