Metadata-Version: 1.0
Name: keras-lightning
Version: 1.0.1
Summary: Minimal Keras like wrapper for torch-lightning
Home-page: https://github.com/Alantlb/keras-lightning
Author: Alan T. L. Bacellar
Author-email: alanbacellar@gmail.com
License: UNKNOWN
Platform: UNKNOWN
